src/__init__.py
src/app/Router.py
src/app/Server.py
src/app/__init__.py
src/app/app.py
src/app/classes/Error.py
src/app/classes/Lib.py
src/app/classes/Response.py
src/app/classes/Semver.py
src/app/classes/__init__.py
src/app/data/__init__.py
src/app/data/dependencies.py
src/app/data/deprecated.py
src/app/data/package.py
src/app/data/updates.py
src/app/data/vulnerabilities.py
src/app/path.py
src/app/utils.py
src/client/css/colors.css
src/client/css/styles.classes.css
src/client/css/styles.components.css
src/client/css/styles.ids.css
src/client/css/styles.main.css
src/client/favicon.ico
src/client/font/Arimo-Bold.woff2
src/client/font/Arimo-Regular.woff2
src/client/font/Arimo-SemiBold.woff2
src/client/index.html
src/client/js/components/dashboard.js
src/client/js/components/elements/dependency-filter.js
src/client/js/components/elements/dependency-info.js
src/client/js/components/elements/dependency-item.js
src/client/js/components/elements/dependency-version.js
src/client/js/components/elements/icon.js
src/client/js/components/elements/index.js
src/client/js/components/elements/select.js
src/client/js/components/elements/table.js
src/client/js/components/index.js
src/client/js/components/items/Item.js
src/client/js/components/items/basic-info.js
src/client/js/components/items/dependencies-list.js
src/client/js/components/items/dependencies-network.js
src/client/js/components/items/dependencies-tree.js
src/client/js/components/items/deprecated-table.js
src/client/js/components/items/frequency.js
src/client/js/components/items/index.js
src/client/js/components/items/issues-table.js
src/client/js/components/items/package-data.js
src/client/js/components/items/updates-table.js
src/client/js/components/items/updates.js
src/client/js/components/items/vulnerabilities-table.js
src/client/js/components/items/vulnerabilities.js
src/client/js/components/items/weight.js
src/client/js/components/popups/Popup.js
src/client/js/components/popups/group-data.js
npm_cockpit-0.4.2.dist-info/METADATA
npm_cockpit-0.4.2.dist-info/WHEEL
npm_cockpit-0.4.2.dist-info/entry_points.txt
npm_cockpit-0.4.2.dist-info/RECORD
