Metadata-Version: 2.1
Name: npm-cockpit
Version: 0.4.2
Summary: Installable command-line tool with web interface which helps to track nodejs project dependencies state
License: MIT
Keywords: command,dashboard,npm,statistic,dependencies,packages,info
Author: Alex Chirkin
Author-email: hello@alexchirkin.me
Requires-Python: >=3.7,<4.0
Classifier: License :: OSI Approved :: MIT License
Classifier: Programming Language :: Python :: 3
Classifier: Programming Language :: Python :: 3.7
Classifier: Programming Language :: Python :: 3.8
Classifier: Programming Language :: Python :: 3.9
Classifier: Programming Language :: Python :: 3.10
Classifier: Programming Language :: Python :: 3.11
Classifier: Programming Language :: Python :: 3.12
Requires-Dist: requests (>=2.28.2,<3.0.0)
